{"uuid":"21451efc1bd7fe90b564e9a0552956267b96ed6d","bioAsHtml":"<p>David Delabassee is a Software Evangelist working in the GlassFish and Java EE Team at Oracle. Prior to that, he spent more than 10 years at Sun Microsystems focusing on Java end-to-end (from the smart card to the high end server) and the developer tools. He has been involved in Java projects since the early days of this technology.\nIn his spare time, he enjoy tinkering and playing with technologies such as Java, Arduino, Home Automation, Linux, Pinball, etc.</p>\n","acceptedTalks":[{"talkType":"Conference","track":"Server Side Java","links":[{"href":"http://cfp.devoxx.be/api/conferences/DV15/talks/CIU-0634","rel":"http://cfp.devoxx.be/api/profile/talk","title":"More details about this talk"},{"href":"http://cfp.devoxx.be/api/conferences/DV15/speakers/21451efc1bd7fe90b564e9a0552956267b96ed6d","rel":"http://cfp.devoxx.be/api/profile/speaker","title":"David Delabassee"},{"href":"http://cfp.devoxx.be/api/conferences/DV15/speakers/35a6797008ce8295fcc76c03dcf0a58a07ab3070","rel":"http://cfp.devoxx.be/api/profile/speaker","title":"José Paumard"}],"id":"CIU-0634","title":"Java SE 8 for Java EE Developers"},{"talkType":"BOF (Bird of a Feather)","track":"Server Side Java","links":[{"href":"http://cfp.devoxx.be/api/conferences/DV15/talks/BBB-1594","rel":"http://cfp.devoxx.be/api/profile/talk","title":"More details about this talk"},{"href":"http://cfp.devoxx.be/api/conferences/DV15/speakers/21451efc1bd7fe90b564e9a0552956267b96ed6d","rel":"http://cfp.devoxx.be/api/profile/speaker","title":"David Delabassee"}],"id":"BBB-1594","title":"Java EE Gathering"}],"company":"Oracle","bio":"David Delabassee is a Software Evangelist working in the GlassFish and Java EE Team at Oracle. Prior to that, he spent more than 10 years at Sun Microsystems focusing on Java end-to-end (from the smart card to the high end server) and the developer tools. He has been involved in Java projects since the early days of this technology.\r\nIn his spare time, he enjoy tinkering and playing with technologies such as Java, Arduino, Home Automation, Linux, Pinball, etc.","lastName":"Delabassee","firstName":"David","blog":"https://plus.google.com/+DavidDelabassee","avatarURL":"https://lh6.googleusercontent.com/-jaxuzv12XUw/AAAAAAAAAAI/AAAAAAAAATI/g8iodvB6-Fo/photo.jpg","twitter":"@delabassee","lang":"en"}