{"uuid":"8ce20b7419146783a7992c29cafadfcba3316df4","bioAsHtml":"<p>Ernest Micklei holds the position of Senior Software Architect at bol.com and has 20+ years of experience in Software Design, Development and Architecture. At bol.com, the largest e-commerce company of the Netherlands, he is responsible for the design and architecture of all internal and external Web Services. In addition, he is working with our operations staff to improve and investigate performance issues related to our Java-based applications and Services.\nHe is currently active in High Performance Websites, REST services and NoSQL and is exited about Google Go. His contributions to the open-source community can be found at github.com/emicklei and emicklei.googlecode.com. He blogs at ernestmicklei.com</p>\n","acceptedTalks":[{"talkType":"Quickie","track":"Future<Devoxx>","links":[{"href":"http://cfp.devoxx.be/api/conferences/DV15/talks/TZA-2142","rel":"http://cfp.devoxx.be/api/profile/talk","title":"More details about this talk"},{"href":"http://cfp.devoxx.be/api/conferences/DV15/speakers/8ce20b7419146783a7992c29cafadfcba3316df4","rel":"http://cfp.devoxx.be/api/profile/speaker","title":"Ernest Micklei"}],"id":"TZA-2142","title":"Let's have 100 phones connected to a cinema multi-player game"}],"company":"bol.com","bio":"Ernest Micklei holds the position of Senior Software Architect at bol.com and has 20+ years of experience in Software Design, Development and Architecture. At bol.com, the largest e-commerce company of the Netherlands, he is responsible for the design and architecture of all internal and external Web Services. In addition, he is working with our operations staff to improve and investigate performance issues related to our Java-based applications and Services.\r\nHe is currently active in High Performance Websites, REST services and NoSQL and is exited about Google Go. His contributions to the open-source community can be found at github.com/emicklei and emicklei.googlecode.com. He blogs at ernestmicklei.com","lastName":"Micklei","firstName":"Ernest","blog":"https://plus.google.com/+ErnestMicklei","avatarURL":"https://lh5.googleusercontent.com/-CllRyO3We0U/AAAAAAAAAAI/AAAAAAAAAJs/0YjcAnDIJxA/photo.jpg","twitter":"@ernestmicklei","lang":"en"}